favorites_crawler/__init__.py
favorites_crawler/exceptions.py
favorites_crawler/itemloaders.py
favorites_crawler/items.py
favorites_crawler/middlewares.py
favorites_crawler/pipelines.py
favorites_crawler/processors.py
favorites_crawler/settings.py
favorites_crawler/commands/__init__.py
favorites_crawler/commands/crawl.py
favorites_crawler/commands/login.py
favorites_crawler/commands/restore.py
favorites_crawler/constants/__init__.py
favorites_crawler/constants/domains.py
favorites_crawler/constants/endpoints.py
favorites_crawler/constants/headers.py
favorites_crawler/constants/path.py
favorites_crawler/constants/regexes.py
favorites_crawler/spiders/__init__.py
favorites_crawler/spiders/lemon.py
favorites_crawler/spiders/nhentai.py
favorites_crawler/spiders/pixiv.py
favorites_crawler/spiders/twitter.py
favorites_crawler/spiders/yandere.py
favorites_crawler/spiders/yandere_vote.py
favorites_crawler/utils/__init__.py
favorites_crawler/utils/auth.py
favorites_crawler/utils/common.py
favorites_crawler/utils/config.py
favorites_crawler/utils/cookies.py
favorites_crawler/utils/files.py
favorites_crawler/utils/text.py
favorites_crawler-1.0.1.dist-info/LICENSE
favorites_crawler-1.0.1.dist-info/METADATA
favorites_crawler-1.0.1.dist-info/WHEEL
favorites_crawler-1.0.1.dist-info/entry_points.txt
favorites_crawler-1.0.1.dist-info/top_level.txt
favorites_crawler-1.0.1.dist-info/RECORD
