Metadata-Version: 2.1
Name: favorites_crawler
Version: 1.0.1
Summary: Crawl your personal favorite images, photo albums, comics from website. Support pixiv, yande.re for now.
Home-page: https://github.com/RyouMon/FavoritesCrawler
Author: RyouMon
Author-email: wenslife@outlook.com
Project-URL: Bug Tracker, https://github.com/RyouMon/FavoritesCrawler/issues
Classifier: Programming Language :: Python :: 3
Classifier: Programming Language :: Python :: 3.10
Classifier: Programming Language :: Python :: 3.11
Classifier: Programming Language :: Python :: 3.12
Classifier: License :: OSI Approved :: MIT License
Classifier: Operating System :: OS Independent
Requires-Python: >=3.10
License-File: LICENSE
Requires-Dist: scrapy>=2.12.0
Requires-Dist: pyyaml>=6.0
Requires-Dist: pyexiftool==0.5.6
Requires-Dist: jsonpath-rw==1.4.0
Requires-Dist: unidecode==1.3.8
Requires-Dist: langdetect==1.0.9
Requires-Dist: pykakasi==2.2.1
Requires-Dist: gppt==4.1.0
Requires-Dist: typer>=0.14.0
Requires-Dist: loguru>=0.7.2
